crimes/__init__.py
crimes/autocommit.py
crimes/compiler.py
crimes/excepthook.py
crimes/exceptions.py
crimes/gcc_diagnostics.py
crimes/importer.py
crimes-0.1.1.dist-info/LICENSE
crimes-0.1.1.dist-info/METADATA
crimes-0.1.1.dist-info/WHEEL
crimes-0.1.1.dist-info/RECORD
