Metadata-Version: 2.1
Name: crimes
Version: 0.1.1
Summary: Import C files into Python, illegally.
Home-page: https://github.com/eddieantonio/crimes
License: Apache-2.0
Author: Eddie Antonio Santos
Author-email: hello@eddieantonio.ca
Requires-Python: >=3.11,<4.0
Classifier: License :: OSI Approved :: Apache Software License
Classifier: Programming Language :: Python :: 3
Classifier: Programming Language :: Python :: 3.11
Classifier: Programming Language :: Python :: 3.12
